arva/__init__.py
arva/arva.py
arva_sdk-0.1.0.dist-info/LICENSE
arva_sdk-0.1.0.dist-info/METADATA
arva_sdk-0.1.0.dist-info/WHEEL
arva_sdk-0.1.0.dist-info/top_level.txt
arva_sdk-0.1.0.dist-info/RECORD
