Metadata-Version: 2.1
Name: arva-sdk
Version: 0.1.0
Summary: A Python SDK for the Arva API
Author-email: Your Name <your.email@example.com>
License: This is free and unencumbered software released into the public domain.
Project-URL: Homepage, https://github.com/Arva-AI/python-sdk
Keywords: arva,sdk,api
Classifier: Development Status :: 3 - Alpha
Classifier: Intended Audience :: Developers
Classifier: License :: OSI Approved :: MIT License
Classifier: Operating System :: OS Independent
Classifier: Programming Language :: Python :: 3
Classifier: Programming Language :: Python :: 3.7
Classifier: Programming Language :: Python :: 3.8
Classifier: Programming Language :: Python :: 3.9
Requires-Python: >=3.7
License-File: LICENSE
Requires-Dist: requests
Requires-Dist: requests-toolbelt
